avocado_i2n/__init__.py
avocado_i2n/cmd_parser.py
avocado_i2n/intertest_setup.py
avocado_i2n/params_parser.py
avocado_i2n/cartgraph/__init__.py
avocado_i2n/cartgraph/graph.py
avocado_i2n/cartgraph/node.py
avocado_i2n/cartgraph/object.py
avocado_i2n/cartgraph/worker.py
avocado_i2n/conf.d/i2n.conf
avocado_i2n/plugins/__init__.py
avocado_i2n/plugins/auto.py
avocado_i2n/plugins/loader.py
avocado_i2n/plugins/manu.py
avocado_i2n/plugins/runner.py
avocado_i2n/plugins/settings.py
avocado_i2n/states/__init__.py
avocado_i2n/states/btrfs.py
avocado_i2n/states/lvm.py
avocado_i2n/states/lxc.py
avocado_i2n/states/pool.py
avocado_i2n/states/qcow2.py
avocado_i2n/states/ramfile.py
avocado_i2n/states/setup.py
avocado_i2n/states/vmnet.py
avocado_i2n/vmnet/__init__.py
avocado_i2n/vmnet/interface.py
avocado_i2n/vmnet/netconfig.py
avocado_i2n/vmnet/network.py
avocado_i2n/vmnet/node.py
avocado_i2n/vmnet/tunnel.py
avocado_i2n/vmnet/templates/all.fwd.template
avocado_i2n/vmnet/templates/dhcpd.conf.template
avocado_i2n/vmnet/templates/dnsmasq.conf.template
avocado_i2n/vmnet/templates/hosts.conf.template
avocado_i2n/vmnet/templates/named.conf.template
avocado_i2n/vmnet/templates/zone.fwd.template
avocado_i2n/vmnet/templates/zone.rev.template
usr/share/avocado-plugins-i2n/tp_folder/configs/groups-base.cfg
usr/share/avocado-plugins-i2n/tp_folder/configs/groups.cfg
usr/share/avocado-plugins-i2n/tp_folder/configs/guest-base.cfg
usr/share/avocado-plugins-i2n/tp_folder/configs/guest-hw.cfg
usr/share/avocado-plugins-i2n/tp_folder/configs/guest-os.cfg
usr/share/avocado-plugins-i2n/tp_folder/configs/guest.cfg
usr/share/avocado-plugins-i2n/tp_folder/configs/nets.cfg
usr/share/avocado-plugins-i2n/tp_folder/configs/objects-overwrite.cfg
usr/share/avocado-plugins-i2n/tp_folder/configs/sets-overwrite.cfg
usr/share/avocado-plugins-i2n/tp_folder/configs/sets.cfg
usr/share/avocado-plugins-i2n/tp_folder/configs/vms.cfg
usr/share/avocado-plugins-i2n/tp_folder/controls/manual.control
avocado_framework_plugin_i2n-103.0.dist-info/LICENSE
avocado_framework_plugin_i2n-103.0.dist-info/METADATA
avocado_framework_plugin_i2n-103.0.dist-info/WHEEL
avocado_framework_plugin_i2n-103.0.dist-info/entry_points.txt
avocado_framework_plugin_i2n-103.0.dist-info/top_level.txt
avocado_framework_plugin_i2n-103.0.dist-info/RECORD
