Metadata-Version: 2.1
Name: avocado-framework-plugin-i2n
Version: 103.0
Summary: Avocado Intra2net Plugins
Home-page: http://github.com/intra2net/avocado-i2n
Author: Intra2net AG
Author-email: support@intra2net.com
License-File: LICENSE
Requires-Dist: avocado-framework-plugin-vt
Requires-Dist: aexpect
